[
  {
    "tags": ["summmer", "mega-discount"],
    "collections": ["seasonal", "dress"],
    "ProductID": "600",
    "Brand": "Salvatori Farregano",
    "SKU": "KOU-908",
    "ProductName": "Off Shoulder Winter Dress",
    "Quantity": 1,
    "ItemPrice": 89.99,
    "RowTotal": 89.99,
    "ProductURL": "https://wwww.corseta-republic.com/catalog_main/products/products/US00",
    "ImageURL": "https://img.simplydresses.com/_img/SDPRODUCTS/2285315/500/ivory-gold-dress-JU-MA-262134-a.jpg",
    "ProductCategories": [
      "Dress"
    ]
  },
  {
    "tags": ["summmer", "full-price"],
    "collections": ["low-budget", "dress", "seasonal"],
    "ProductID": "601",
    "Brand": "ZAVA",
    "SKU": "POG-879",
    "ProductName": "Navy Dinner Date Dress",
    "Quantity": 1,
    "ItemPrice": 123.79,
    "RowTotal": 123.79,
    "ProductURL": "https://wwww.corseta-republic.com/catalog_main/products/products/US01",
    "ImageURL": "https://cdn2.citychiconline.com/media/catalog/product/cache/f38713d27106efaeaccd98fe2a3b4e5f/149568NAVY-1.jpg",
    "ProductCategories": [
      "Female"
    ]
  },
  {
    "tags": ["winter", "mega-discount"],
    "collections": ["low-budget", "dress", "seasonal"],
    "ProductID": "602",
    "Brand": "Club Monaco",
    "SKU": "KIY-019",
    "ProductName": "Royal Blue Evening Dress",
    "Quantity": 1,
    "ItemPrice": 178.22,
    "RowTotal": 178.22,
    "ProductURL": "https://wwww.corseta-republic.com/catalog_main/products/products/US02",
    "ImageURL": "https://www.dhresource.com/0x0/f2/albu/g8/M00/EF/3D/rBVaV1xJLA6ATtkCAADdIK0yKBk679.jpg",
    "ProductCategories": [
      "Female"
    ]
  },
  {
    "tags": ["summmer", "full-price"],
    "collections": ["low-budget", "dress", "seasonal"],
    "ProductID": "603",
    "Brand": "Cosmopolitan",
    "SKU": "KIY-019",
    "ProductName": "Royal Blue Evening Dress",
    "Quantity": 1,
    "ItemPrice": 178.22,
    "RowTotal": 178.22,
    "ProductURL": "https://wwww.corseta-republic.com/catalog_main/products/products/US03",
    "ImageURL": "https://www.dhresource.com/0x0/f2/albu/g8/M00/EF/3D/rBVaV1xJLA6ATtkCAADdIK0yKBk679.jpg",
    "ProductCategories": [
      "Female"
    ]
  },
  {
    "tags": ["summmer", "full-price"],
    "collections": ["low-budget", "dress", "seasonal"],
    "ProductID": "604",
    "Brand": "Salvatori Boch",
    "SKU": "GRR-559",
    "ProductName": "Flower Pink Wedding Dress",
    "Quantity": 1,
    "ItemPrice": 165.22,
    "RowTotal": 165.22,
    "ProductURL": "https://wwww.corseta-republic.com/catalog_main/products/products/US04",
    "ImageURL": "https://cdn.shopify.com/s/files/1/2375/3611/products/70e9c190f6ed4c340f81319f8d2967cb_600x.jpg?v=1569290053",
    "ProductCategories": [
      "Female"
    ]
  },
  {
    "tags": ["spring", "full-price"],
    "collections": ["low-budget", "upper-body", "seasonal"],
    "ProductID": "605",
    "Brand": "Polo",
    "SKU": "JKU-554",
    "ProductName": "Two Piece Grey Blazzer",
    "Quantity": 1,
    "ItemPrice": 183.22,
    "RowTotal": 183.22,
    "ProductURL": "https://wwww.corseta-republic.com/catalog_main/products/products/US05",
    "ImageURL": "https://img1.cfcdn.club/06/eb/06b6133243ea1304682a7a4ab122d0eb_350x350.jpg",
    "ProductCategories": [
      "Male",
      "Blazzer"
    ]
  },
  {
    "tags": ["spring", "full-price"],
    "collections": ["low-budget", "upper-body", "seasonal"],
    "ProductID": "606",
    "Brand": "Gucci",
    "SKU": "PLU-098",
    "ProductName": "Blue Slim Fit Blazzer",
    "Quantity": 1,
    "ItemPrice": 193.22,
    "RowTotal": 193.22,
    "ProductURL": "https://wwww.corseta-republic.com/catalog_main/products/products/US06",
    "ImageURL": "http://www.choicemart.in/wp-content/uploads/2019/07/BLUE-BLAZER.jpg",
    "ProductCategories": [
      "Male",
      "Blazzer"
    ]
  },
  {
    "tags": ["spring", "full-price"],
    "collections": ["low-budget", "upper-body", "seasonal"],
    "ProductID": "607",
    "Brand": "Polo",
    "SKU": "LUO-045",
    "ProductName": "Brown Hazion Style Blazzer",
    "Quantity": 1,
    "ItemPrice": 177.22,
    "RowTotal": 177.22,
    "ProductURL": "https://wwww.corseta-republic.com/catalog_main/products/products/US07",
    "ImageURL": "https://i0.wp.com/halcyonkids.us/wp-content/uploads/2016/08/asos-skinny-cotton-blazer-1-1.jpg?resize=300%2C300&ssl=1",
    "ProductCategories": [
      "Male",
      "Blazzer"
    ]
  },
  {
    "tags": ["spring", "full-price"],
    "collections": ["low-budget", "shoes", "seasonal"],
    "ProductID": "608",
    "Brand": "Shoedazed",
    "SKU": "PBR-987",
    "ProductName": "Pointed Shallow Toe Shoes",
    "Quantity": 1,
    "ItemPrice": 143.22,
    "RowTotal": 143.22,
    "ProductURL": "https://wwww.corseta-republic.com/catalog_main/products/products/US08",
    "ImageURL": "https://shoedazed.com/image/cache/catalog/Asumer//ASUMER-2019-new-pumps-women-shoes-pointed-toe-shallow-high-heels-shoes-flock-prom-wedding-shoes-floc-32972390175-9044-550x550.jpeg",
    "ProductCategories": [
      "Female",
    ]
  },
  {
    "tags": ["summmer", "full-price"],
    "collections": ["blowout-collection", "shoes", "seasonal"],
    "ProductID": "609",
    "Brand": "Jimmy Choo",
    "SKU": "OIY-991",
    "ProductName": "Black Lavish Shoes",
    "Quantity": 1,
    "ItemPrice": 123.22,
    "RowTotal": 123.22,
    "ProductURL": "https://wwww.corseta-republic.com/catalog_main/products/products/US09",
    "ImageURL": "https://cdn.cliqueinc.com/posts/281360/most-expensive-shoe-brands-281360-1563486702201-main.700x0c.jpg",
    "ProductCategories": [
      "Female",
    ]
  },
  {
    "tags": ["summmer", "full-price"],
    "collections": ["low-budget", "shoes", "seasonal"],
    "ProductID": "610",
    "Brand": "Jimmy Choo",
    "SKU": "LKE-723",
    "ProductName": "Formal Black Shoes",
    "Quantity": 1,
    "ItemPrice": 128.22,
    "RowTotal": 128.22,
    "ProductURL": "https://wwww.corseta-republic.com/catalog_main/products/products/US10",
    "ImageURL": "https://ae01.alicdn.com/kf/HTB1lFMKIFXXXXc_XFXXq6xXFXXXz/Soft-outsole-formal-shoes-women-female-leather-genuine-leather-thick-heel-work-shoes-female-black-medium.jpg_640x640.jpg",
    "ProductCategories": [
      "Female",
      "Formal"
    ]
  },
  {
    "tags": ["winter", "full-price"],
    "collections": ["low-budget", "shoes", "seasonal"],
    "ProductID": "611",
    "Brand": "Christian Lambottini",
    "SKU": "UHY-231",
    "ProductName": "Clear Animal Printed Stiletto",
    "Quantity": 1,
    "ItemPrice": 102.56,
    "RowTotal": 102.56,
    "ProductURL": "https://wwww.corseta-republic.com/catalog_main/products/products/US11",
    "ImageURL": "https://i.pinimg.com/originals/ee/19/0e/ee190e0159b6113b51f2939698f68fc8.jpg",
    "ProductCategories": [
      "Formal"
    ]
  }
]
